embodycodec/__init__.py
embodycodec/attributes.py
embodycodec/codec.py
embodycodec/crc.py
embodycodec/exceptions.py
embodycodec/file_codec.py
embodycodec/py.typed
embodycodec/types.py
embody_codec-1.0.39.dist-info/METADATA
embody_codec-1.0.39.dist-info/WHEEL
embody_codec-1.0.39.dist-info/licenses/LICENSE
embody_codec-1.0.39.dist-info/RECORD
