Metadata-Version: 2.4
Name: embody-codec
Version: 1.0.39
Summary: Embody Codec
Project-URL: Changelog, https://github.com/aidee-health/embody-codec/releases
Project-URL: Homepage, https://github.com/aidee-health/embody-codec
Project-URL: Repository, https://github.com/aidee-health/embody-codec
Author-email: Aidee Health AS <hello@aidee.io>
License-Expression: MIT
License-File: LICENSE
Classifier: Development Status :: 5 - Production/Stable
Requires-Python: <4.0,>=3.11
